sweetrpg_web_core/__init__.py
sweetrpg_web_core/constants.py
sweetrpg_web_core/errors.py
sweetrpg_web_core/blueprints/__init__.py
sweetrpg_web_core/blueprints/health/__init__.py
sweetrpg_web_core/helpers/__init__.py
sweetrpg_web_core/helpers/context.py
sweetrpg_web_core-0.0.697.dist-info/LICENSE
sweetrpg_web_core-0.0.697.dist-info/METADATA
sweetrpg_web_core-0.0.697.dist-info/WHEEL
sweetrpg_web_core-0.0.697.dist-info/entry_points.txt
sweetrpg_web_core-0.0.697.dist-info/top_level.txt
sweetrpg_web_core-0.0.697.dist-info/RECORD
