Metadata-Version: 2.1
Name: sweetrpg-web-core
Version: 0.0.697
Home-page: https://sweetrpg.com
Author: Paul Schifferer
Author-email: dm@sweetrpg.com
License: MIT
Project-URL: Documentation, https://sweetrpg.github.io/web-core
Classifier: Development Status :: 3 - Alpha
Classifier: Environment :: Web Environment
Classifier: Framework :: Flask
Classifier: Intended Audience :: Developers
Classifier: License :: OSI Approved :: MIT License
Classifier: Operating System :: OS Independent
Classifier: Programming Language :: Python
Classifier: Topic :: Software Development :: Libraries :: Application Frameworks
License-File: LICENSE
Requires-Dist: Flask~=3.0
